tgzr/nice/__init__.py
tgzr/nice/_version.py
tgzr/nice/tgzr_visid.py
tgzr/nice/theme.py
tgzr/nice/controls/__init__.py
tgzr/nice/controls/breadcrumbs.py
tgzr/nice/controls/chips.py
tgzr/nice/controls/box_selector/__init__.py
tgzr/nice/controls/box_selector/box_selector.js
tgzr/nice/data_elements/__init__.py
tgzr/nice/data_elements/dict_tree.py
tgzr/nice/data_elements/contextual_settings_view/__init__.py
tgzr/nice/data_elements/node_graph/__init__.py
tgzr/nice/data_elements/node_graph/node_graph.js
tgzr/nice/layout/__init__.py
tgzr/nice/layout/movable/__init__.py
tgzr/nice/layout/movable/movable.js
tgzr/nice/layout/movable/movable_container.js
tgzr/nice/layout/sortable/__init__.py
tgzr/nice/layout/sortable/sortable.js
tgzr/nice/static_files/__init__.py
tgzr/nice/static_files/tgzr_assets/__init__.py
tgzr/nice/static_files/tgzr_assets/brands/graal-network.webp
tgzr/nice/static_files/tgzr_assets/brands/miyu.svg
tgzr/nice/static_files/tgzr_assets/favicon/android-chrome-192x192.png
tgzr/nice/static_files/tgzr_assets/favicon/android-chrome-512x512.png
tgzr/nice/static_files/tgzr_assets/favicon/apple-touch-icon.png
tgzr/nice/static_files/tgzr_assets/favicon/favicon-16x16.png
tgzr/nice/static_files/tgzr_assets/favicon/favicon-32x32.png
tgzr/nice/static_files/tgzr_assets/favicon/favicon.ico
tgzr/nice/static_files/tgzr_assets/favicon/site.webmanifest
tgzr/nice/static_files/tgzr_assets/other/cc-by-sa.png
tgzr/nice/static_files/tgzr_assets/tgzr/logo_only_banner_black.png
tgzr/nice/static_files/tgzr_assets/tgzr/tgzr-org-qr-code.svg
tgzr/nice/static_files/tgzr_assets/tgzr/tgzr_banner_linkedin.png
tgzr/nice/static_files/tgzr_assets/tgzr/tgzr_logo.css
tgzr/nice/static_files/tgzr_assets/tgzr/tgzr_logo.svg
tgzr/nice/static_files/tgzr_assets/tgzr/tgzr_logo_anim.css
tgzr/nice/static_files/tgzr_assets/tgzr/tgzr_logo_bgblack.svg
tgzr/nice/static_files/tgzr_assets/tgzr/tgzr_thumbnail.png
tgzr/nice/static_files/tgzr_medias/__init__.py
tgzr/nice/tgzrui/__init__.py
tgzr/nice/tgzrui/demo.py
tgzr_nice-0.100.dist-info/METADATA
tgzr_nice-0.100.dist-info/WHEEL
tgzr_nice-0.100.dist-info/licenses/LICENSE
tgzr_nice-0.100.dist-info/RECORD
