Metadata-Version: 2.4
Name: tgzr.nice
Version: 0.100
Summary: Components and tools for TGZR nice apps
Project-URL: Documentation, https://github.com/open-tgzr/tgzr.nice#readme
Project-URL: Issues, https://github.com/open-tgzr/tgzr.nice/issues
Project-URL: Source, https://github.com/open-tgzr/tgzr.nice
Author-email: Dee <dee.sometech@gmail.com>
License-Expression: GPL-3.0-or-later
License-File: LICENSE
Classifier: Development Status :: 4 - Beta
Classifier: Programming Language :: Python
Classifier: Programming Language :: Python :: 3.8
Classifier: Programming Language :: Python :: 3.9
Classifier: Programming Language :: Python :: 3.10
Classifier: Programming Language :: Python :: 3.11
Classifier: Programming Language :: Python :: 3.12
Classifier: Programming Language :: Python :: Implementation :: CPython
Classifier: Programming Language :: Python :: Implementation :: PyPy
Requires-Python: >=3.9
Requires-Dist: nicegui>=2.24.2
Requires-Dist: pydantic-settings>=2.8.1
